[
  {
    "id": "si28151",
    "x": 47,
    "y": 49,
    "width": 785,
    "height": 271,
    "imagePath": "dr/4044_785_271.png",
    "uid": 28151
  },
  {
    "id": "si28153",
    "x": 711,
    "y": 1,
    "width": 96,
    "height": 97,
    "imagePath": "dr/4034_96_97.png",
    "uid": 28153
  },
  {
    "id": "si28157",
    "x": 91,
    "y": 1,
    "width": 96,
    "height": 97,
    "imagePath": "dr/4039_96_97.png",
    "uid": 28157
  },
  {
    "id": "si33702",
    "x": 47,
    "y": 49,
    "width": 785,
    "height": 271,
    "imagePath": "dr/4044_785_271.png",
    "uid": 33702
  },
  {
    "id": "si33704",
    "x": 711,
    "y": 1,
    "width": 96,
    "height": 97,
    "imagePath": "dr/4034_96_97.png",
    "uid": 33704
  },
  {
    "id": "si33708",
    "x": 91,
    "y": 1,
    "width": 96,
    "height": 97,
    "imagePath": "dr/4039_96_97.png",
    "uid": 33708
  },
  {
    "id": "si33953",
    "x": 47,
    "y": 49,
    "width": 785,
    "height": 271,
    "imagePath": "dr/4044_785_271.png",
    "uid": 33953
  },
  {
    "id": "si33955",
    "x": 711,
    "y": 1,
    "width": 96,
    "height": 97,
    "imagePath": "dr/4034_96_97.png",
    "uid": 33955
  },
  {
    "id": "si33959",
    "x": 91,
    "y": 1,
    "width": 96,
    "height": 97,
    "imagePath": "dr/4039_96_97.png",
    "uid": 33959
  },
  {
    "id": "si38735",
    "x": 641,
    "y": 298,
    "width": 114,
    "height": 33,
    "imagePath": "dr/si38735.png",
    "uid": 38735
  },
  {
    "id": "si38818",
    "x": 641,
    "y": 258,
    "width": 114,
    "height": 33,
    "imagePath": "dr/si38818.png",
    "uid": 38818
  },
  {
    "id": "si38804",
    "x": 641,
    "y": 220,
    "width": 114,
    "height": 33,
    "imagePath": "dr/si38804.png",
    "uid": 38804
  },
  {
    "id": "si31384",
    "x": 47,
    "y": 49,
    "width": 785,
    "height": 271,
    "imagePath": "dr/4044_785_271.png",
    "uid": 31384
  },
  {
    "id": "si31386",
    "x": 711,
    "y": 1,
    "width": 96,
    "height": 97,
    "imagePath": "dr/4034_96_97.png",
    "uid": 31386
  },
  {
    "id": "si31390",
    "x": 91,
    "y": 1,
    "width": 96,
    "height": 97,
    "imagePath": "dr/4039_96_97.png",
    "uid": 31390
  },
  {
    "id": "si39915",
    "x": 47,
    "y": 49,
    "width": 785,
    "height": 271,
    "imagePath": "dr/4044_785_271.png",
    "uid": 39915
  },
  {
    "id": "si39917",
    "x": 711,
    "y": 1,
    "width": 96,
    "height": 97,
    "imagePath": "dr/4034_96_97.png",
    "uid": 39917
  },
  {
    "id": "si39921",
    "x": 91,
    "y": 1,
    "width": 96,
    "height": 97,
    "imagePath": "dr/4039_96_97.png",
    "uid": 39921
  },
  {
    "id": "si31810",
    "x": 47,
    "y": 49,
    "width": 785,
    "height": 271,
    "imagePath": "dr/4044_785_271.png",
    "uid": 31810
  },
  {
    "id": "si31812",
    "x": 711,
    "y": 1,
    "width": 96,
    "height": 97,
    "imagePath": "dr/4034_96_97.png",
    "uid": 31812
  },
  {
    "id": "si31816",
    "x": 91,
    "y": 1,
    "width": 96,
    "height": 97,
    "imagePath": "dr/4039_96_97.png",
    "uid": 31816
  },
  {
    "id": "si40212",
    "x": 47,
    "y": 49,
    "width": 785,
    "height": 271,
    "imagePath": "dr/4044_785_271.png",
    "uid": 40212
  },
  {
    "id": "si40214",
    "x": 711,
    "y": 1,
    "width": 96,
    "height": 97,
    "imagePath": "dr/4034_96_97.png",
    "uid": 40214
  },
  {
    "id": "si40218",
    "x": 91,
    "y": 1,
    "width": 96,
    "height": 97,
    "imagePath": "dr/4039_96_97.png",
    "uid": 40218
  },
  {
    "id": "si37648",
    "x": 47,
    "y": 49,
    "width": 785,
    "height": 271,
    "imagePath": "dr/4044_785_271.png",
    "uid": 37648
  },
  {
    "id": "si37650",
    "x": 711,
    "y": 1,
    "width": 96,
    "height": 97,
    "imagePath": "dr/4034_96_97.png",
    "uid": 37650
  },
  {
    "id": "si37654",
    "x": 91,
    "y": 1,
    "width": 96,
    "height": 97,
    "imagePath": "dr/4039_96_97.png",
    "uid": 37654
  },
  {
    "id": "si33302",
    "x": 47,
    "y": 49,
    "width": 785,
    "height": 271,
    "imagePath": "dr/4044_785_271.png",
    "uid": 33302
  },
  {
    "id": "si33304",
    "x": 711,
    "y": 1,
    "width": 96,
    "height": 97,
    "imagePath": "dr/4034_96_97.png",
    "uid": 33304
  },
  {
    "id": "si33308",
    "x": 91,
    "y": 1,
    "width": 96,
    "height": 97,
    "imagePath": "dr/4039_96_97.png",
    "uid": 33308
  },
  {
    "id": "si18444",
    "x": 47,
    "y": 49,
    "width": 785,
    "height": 271,
    "imagePath": "dr/4044_785_271.png",
    "uid": 18444
  },
  {
    "id": "si18446",
    "x": 711,
    "y": 1,
    "width": 96,
    "height": 97,
    "imagePath": "dr/4034_96_97.png",
    "uid": 18446
  },
  {
    "id": "si18450",
    "x": 91,
    "y": 1,
    "width": 96,
    "height": 97,
    "imagePath": "dr/4039_96_97.png",
    "uid": 18450
  },
  {
    "id": "si22697",
    "x": 47,
    "y": 49,
    "width": 785,
    "height": 271,
    "imagePath": "dr/4044_785_271.png",
    "uid": 22697
  },
  {
    "id": "si22699",
    "x": 711,
    "y": 1,
    "width": 96,
    "height": 97,
    "imagePath": "dr/4034_96_97.png",
    "uid": 22699
  },
  {
    "id": "si22703",
    "x": 91,
    "y": 1,
    "width": 96,
    "height": 97,
    "imagePath": "dr/4039_96_97.png",
    "uid": 22703
  },
  {
    "id": "si4756",
    "x": 47,
    "y": 49,
    "width": 785,
    "height": 271,
    "imagePath": "dr/4044_785_271.png",
    "uid": 4756
  },
  {
    "id": "si4758",
    "x": 711,
    "y": 1,
    "width": 96,
    "height": 97,
    "imagePath": "dr/4034_96_97.png",
    "uid": 4758
  },
  {
    "id": "si4762",
    "x": 91,
    "y": 1,
    "width": 96,
    "height": 97,
    "imagePath": "dr/4039_96_97.png",
    "uid": 4762
  },
  {
    "id": "si23950",
    "x": 47,
    "y": 49,
    "width": 785,
    "height": 271,
    "imagePath": "dr/4044_785_271.png",
    "uid": 23950
  },
  {
    "id": "si23952",
    "x": 711,
    "y": 1,
    "width": 96,
    "height": 97,
    "imagePath": "dr/4034_96_97.png",
    "uid": 23952
  },
  {
    "id": "si23956",
    "x": 91,
    "y": 1,
    "width": 96,
    "height": 97,
    "imagePath": "dr/4039_96_97.png",
    "uid": 23956
  },
  {
    "id": "si7174",
    "x": 47,
    "y": 49,
    "width": 785,
    "height": 271,
    "imagePath": "dr/4044_785_271.png",
    "uid": 7174
  },
  {
    "id": "si7176",
    "x": 711,
    "y": 1,
    "width": 96,
    "height": 97,
    "imagePath": "dr/4034_96_97.png",
    "uid": 7176
  },
  {
    "id": "si7180",
    "x": 91,
    "y": 1,
    "width": 96,
    "height": 97,
    "imagePath": "dr/4039_96_97.png",
    "uid": 7180
  },
  {
    "id": "si8702",
    "x": 47,
    "y": 49,
    "width": 785,
    "height": 271,
    "imagePath": "dr/4044_785_271.png",
    "uid": 8702
  },
  {
    "id": "si8704",
    "x": 711,
    "y": 1,
    "width": 96,
    "height": 97,
    "imagePath": "dr/4034_96_97.png",
    "uid": 8704
  },
  {
    "id": "si8708",
    "x": 91,
    "y": 1,
    "width": 96,
    "height": 97,
    "imagePath": "dr/4039_96_97.png",
    "uid": 8708
  },
  {
    "id": "si8888",
    "x": 47,
    "y": 49,
    "width": 785,
    "height": 271,
    "imagePath": "dr/4044_785_271.png",
    "uid": 8888
  },
  {
    "id": "si8890",
    "x": 711,
    "y": 1,
    "width": 96,
    "height": 97,
    "imagePath": "dr/4034_96_97.png",
    "uid": 8890
  },
  {
    "id": "si8894",
    "x": 91,
    "y": 1,
    "width": 96,
    "height": 97,
    "imagePath": "dr/4039_96_97.png",
    "uid": 8894
  },
  {
    "id": "si9078",
    "x": 47,
    "y": 49,
    "width": 785,
    "height": 271,
    "imagePath": "dr/4044_785_271.png",
    "uid": 9078
  },
  {
    "id": "si9080",
    "x": 711,
    "y": 1,
    "width": 96,
    "height": 97,
    "imagePath": "dr/4034_96_97.png",
    "uid": 9080
  },
  {
    "id": "si9084",
    "x": 91,
    "y": 1,
    "width": 96,
    "height": 97,
    "imagePath": "dr/4039_96_97.png",
    "uid": 9084
  },
  {
    "id": "si9250",
    "x": 47,
    "y": 49,
    "width": 785,
    "height": 271,
    "imagePath": "dr/4044_785_271.png",
    "uid": 9250
  },
  {
    "id": "si9252",
    "x": 711,
    "y": 1,
    "width": 96,
    "height": 97,
    "imagePath": "dr/4034_96_97.png",
    "uid": 9252
  },
  {
    "id": "si9256",
    "x": 91,
    "y": 1,
    "width": 96,
    "height": 97,
    "imagePath": "dr/4039_96_97.png",
    "uid": 9256
  },
  {
    "id": "si9422",
    "x": 47,
    "y": 49,
    "width": 785,
    "height": 271,
    "imagePath": "dr/4044_785_271.png",
    "uid": 9422
  },
  {
    "id": "si9424",
    "x": 711,
    "y": 1,
    "width": 96,
    "height": 97,
    "imagePath": "dr/4034_96_97.png",
    "uid": 9424
  },
  {
    "id": "si9428",
    "x": 91,
    "y": 1,
    "width": 96,
    "height": 97,
    "imagePath": "dr/4039_96_97.png",
    "uid": 9428
  },
  {
    "id": "si9594",
    "x": 47,
    "y": 49,
    "width": 785,
    "height": 271,
    "imagePath": "dr/4044_785_271.png",
    "uid": 9594
  },
  {
    "id": "si9596",
    "x": 711,
    "y": 1,
    "width": 96,
    "height": 97,
    "imagePath": "dr/4034_96_97.png",
    "uid": 9596
  },
  {
    "id": "si9600",
    "x": 91,
    "y": 1,
    "width": 96,
    "height": 97,
    "imagePath": "dr/4039_96_97.png",
    "uid": 9600
  },
  {
    "id": "si39594",
    "x": 47,
    "y": 49,
    "width": 785,
    "height": 271,
    "imagePath": "dr/4044_785_271.png",
    "uid": 39594
  },
  {
    "id": "si39596",
    "x": 711,
    "y": 1,
    "width": 96,
    "height": 97,
    "imagePath": "dr/4034_96_97.png",
    "uid": 39596
  },
  {
    "id": "si39600",
    "x": 91,
    "y": 1,
    "width": 96,
    "height": 97,
    "imagePath": "dr/4039_96_97.png",
    "uid": 39600
  }
]